graml/__init__.py
graml/main.py
graml-0.0.1.dist-info/LICENSE
graml-0.0.1.dist-info/METADATA
graml-0.0.1.dist-info/WHEEL
graml-0.0.1.dist-info/top_level.txt
graml-0.0.1.dist-info/RECORD
