Metadata-Version: 2.1
Name: graml
Version: 0.0.1
Summary: AutoML Framework developed by Bizerba AI Team. Work in progress.
Home-page: https://dev.azure.com/matthiasrieger/ImageRecognition/_git/ir-graml-core
Author: Bizerba AI Team
Author-email: pascal.iwohn@bizerba.com
License: UNKNOWN
Project-URL: Bug Tracker, https://dev.azure.com/matthiasrieger/ImageRecognition/_git/ir-graml-core/issues
Platform: UNKNOWN
Classifier: Programming Language :: Python :: 3
Classifier: License :: OSI Approved :: MIT License
Classifier: Operating System :: OS Independent
Requires-Python: >=3.6
License-File: LICENSE
